pyeconfig/__init__.py
pyeconfig/pyeconfig.py
pyeconfig-0.1.0.dist-info/LICENSE
pyeconfig-0.1.0.dist-info/METADATA
pyeconfig-0.1.0.dist-info/WHEEL
pyeconfig-0.1.0.dist-info/top_level.txt
pyeconfig-0.1.0.dist-info/RECORD
